MANIFEST.in
README.md
setup.py
ldapom/__init__.py
ldapom/attribute.py
ldapom/cdef.py
ldapom/compat.py
ldapom/connection.py
ldapom/entry.py
ldapom/error.py
ldapom.egg-info/PKG-INFO
ldapom.egg-info/SOURCES.txt
ldapom.egg-info/dependency_links.txt
ldapom.egg-info/not-zip-safe
ldapom.egg-info/requires.txt
ldapom.egg-info/top_level.txt
ldapom/__pycache__/_cffi__x1a35ed45xf2e73be8.c
ldapom/__pycache__/_cffi__x9a871d0dxf45fbc6f.c
ldapom/__pycache__/_cffi__xba28fc3fxafca1488.c