Metadata-Version: 1.0
Name: ldapom
Version: 0.12.1
Summary: A pythonic LDAP to Python object mapper
Home-page: https://github.com/leonhandreke/ldapom
Author: UNKNOWN
Author-email: UNKNOWN
License: MIT
Keywords: ldap object mapper
Platform: UNKNOWN
